sql_to_pypika/__init__.py
sql_to_pypika/builders.py
sql_to_pypika/decorators.py
sql_to_pypika/evaluator.py
sql_to_pypika/exceptions.py
sql_to_pypika/lexer.py
sql_to_pypika/parser.py
sql_to_pypika-0.1.3.dist-info/LICENSE
sql_to_pypika-0.1.3.dist-info/WHEEL
sql_to_pypika-0.1.3.dist-info/METADATA
sql_to_pypika-0.1.3.dist-info/RECORD
