Metadata-Version: 2.1
Name: sql-to-pypika
Version: 0.1.3
Summary: Convert raw SQL to Pypika Objects
Home-page: https://github.com/pahwaranger/sql_to_pypika
License: MIT
Keywords: pypika,sql
Author: Amit Pahwa
Author-email: amit@amitpahwa.com
Requires-Python: >=3.8,<4.0
Classifier: License :: OSI Approved :: MIT License
Classifier: Programming Language :: Python :: 3
Classifier: Programming Language :: Python :: 3.10
Classifier: Programming Language :: Python :: 3.8
Classifier: Programming Language :: Python :: 3.9
Requires-Dist: PyPika (>=0.48.9,<0.49.0)
Requires-Dist: sly (>=0.4,<0.5)
Project-URL: Repository, https://github.com/pahwaranger/sql_to_pypika
